ModelFaker/ModelFaker.py
ModelFaker/__init__.py
ModelFaker/Enum/ModelColumnTypesEnum.py
ModelFaker/Enum/ModelRelationTypesEnum.py
ModelFaker/Enum/__init__.py
JTRFaker-1.1.0.dist-info/LICENSE
JTRFaker-1.1.0.dist-info/METADATA
JTRFaker-1.1.0.dist-info/WHEEL
JTRFaker-1.1.0.dist-info/top_level.txt
JTRFaker-1.1.0.dist-info/RECORD
