Metadata-Version: 2.1
Name: JTRFaker
Version: 1.1.0
Summary: A library to generate fake data for various use cases
Home-page: https://github.com/LeanderCS/JTRFaker
Author: Leander Cain Slotosch
Author-email: slotosch.leander@outlook.de
License: UNKNOWN
Platform: UNKNOWN
Classifier: Programming Language :: Python :: 3
Classifier: License :: OSI Approved :: MIT License
Classifier: Operating System :: OS Independent
Requires-Python: >=3.9
License-File: LICENSE
Requires-Dist: SQLAlchemy>=1.3
Requires-Dist: Faker>=10.0.0
